rest_client_framework/__init__.py
rest_client_framework/client.py
rest_client_framework/datastructures.py
rest_client_framework/exceptions.py
rest_client_framework/request.py
rest_client_framework/response.py
rest_client_framework/rest.py
rest_client_framework/test_utils.py
rest_client_framework-0.4.dist-info/COPYING
rest_client_framework-0.4.dist-info/METADATA
rest_client_framework-0.4.dist-info/WHEEL
rest_client_framework-0.4.dist-info/top_level.txt
rest_client_framework-0.4.dist-info/RECORD
