Metadata-Version: 2.1
Name: rest-client-framework
Version: 0.4
Summary: Framework for building REST API clients.
Home-page: https://github.com/mcrowepfx/REST-Client-Framework
Author: Max Crowe
Author-email: max.crowe@performics.com
License: UNKNOWN
Platform: UNKNOWN
Classifier: Programming Language :: Python :: 3
Classifier: License :: OSI Approved :: GNU General Public License v3 (GPLv3)
Classifier: Operating System :: OS Independent
Classifier: Topic :: Software Development :: Libraries :: Python Modules
Requires-Python: >=3.6
License-File: COPYING
Requires-Dist: requests
